seekdb/__init__.py
seekdb-0.0.1.dist-info/METADATA
seekdb-0.0.1.dist-info/WHEEL
seekdb-0.0.1.dist-info/top_level.txt
seekdb-0.0.1.dist-info/RECORD
